jma_feed/__init__.py
jma_feed/feed.py
jma_feed/report.py
jma_feed/tests/__init__.py
jma_feed/tests/conftest.py
jma_feed/tests/resources/__init__.py
jma_feed/tests/resources/sample_mete1.xml
jma_feed/tests/resources/sample_mete2.xml
jma_feed/tests/resources/sample_regular.xml
jma_feed/tests/resources/sample_seis1.xml
jma_feed/tests/resources/sample_volc1.xml
jma_feed/tests/test_feed.py
jma_feed/tests/test_report.py
jma_feed/xml.py
jma_feed-0.9.0.dist-info/LICENSE.md
jma_feed-0.9.0.dist-info/WHEEL
jma_feed-0.9.0.dist-info/METADATA
jma_feed-0.9.0.dist-info/RECORD
